streamlit_process_manager/__init__.py
streamlit_process_manager/_core.py
streamlit_process_manager/api.py
streamlit_process_manager/group.py
streamlit_process_manager/manager.py
streamlit_process_manager/monitor.py
streamlit_process_manager/process.py
streamlit_process_manager/proxy.py
streamlit_process_manager/types.py
streamlit_process_manager-0.0.1a0.dist-info/METADATA
streamlit_process_manager-0.0.1a0.dist-info/WHEEL
streamlit_process_manager-0.0.1a0.dist-info/top_level.txt
streamlit_process_manager-0.0.1a0.dist-info/RECORD
